nut_definitions/__init__.py
nut_definitions/nut_commands.py
nut_definitions/nut_enums.py
nut_definitions/nut_errors.py
nut_definitions/nut_variables.py
nut_definitions-0.0.2.dist-info/licenses/LICENSE
nut_definitions-0.0.2.dist-info/METADATA
nut_definitions-0.0.2.dist-info/WHEEL
nut_definitions-0.0.2.dist-info/top_level.txt
nut_definitions-0.0.2.dist-info/RECORD
