Metadata-Version: 2.4
Name: nut-definitions
Version: 0.0.2
Summary: NUT Definitions
Home-page: https://github.com/Patrick762/nut-definitions
Author: Patrick762
Author-email: <pip-nut-definitions@hosting-rt.de>
Classifier: Development Status :: 1 - Planning
Classifier: Intended Audience :: Developers
Classifier: Programming Language :: Python :: 3
License-File: LICENSE
Dynamic: author
Dynamic: author-email
Dynamic: classifier
Dynamic: description
Dynamic: description-content-type
Dynamic: home-page
Dynamic: license-file
Dynamic: summary
